odoo/addons/l10n_ch_partner_company_type/README.rst
odoo/addons/l10n_ch_partner_company_type/__init__.py
odoo/addons/l10n_ch_partner_company_type/__manifest__.py
odoo/addons/l10n_ch_partner_company_type/data/company_type.xml
odoo/addons/l10n_ch_partner_company_type/i18n/l10n_ch_partner_company_type.pot
odoo/addons/l10n_ch_partner_company_type/readme/CONTRIBUTORS.rst
odoo/addons/l10n_ch_partner_company_type/readme/DESCRIPTION.rst
odoo/addons/l10n_ch_partner_company_type/static/description/icon.png
odoo/addons/l10n_ch_partner_company_type/static/description/index.html
odoo_addon_l10n_ch_partner_company_type-16.0.1.0.0.2.dist-info/METADATA
odoo_addon_l10n_ch_partner_company_type-16.0.1.0.0.2.dist-info/WHEEL
odoo_addon_l10n_ch_partner_company_type-16.0.1.0.0.2.dist-info/top_level.txt
odoo_addon_l10n_ch_partner_company_type-16.0.1.0.0.2.dist-info/RECORD
